setup.py
sunnyday_api_weather/__init__.py
sunnyday_api_weather/sunnyday_api_weather.py
sunnyday_api_weather.egg-info/PKG-INFO
sunnyday_api_weather.egg-info/SOURCES.txt
sunnyday_api_weather.egg-info/dependency_links.txt
sunnyday_api_weather.egg-info/requires.txt
sunnyday_api_weather.egg-info/top_level.txt